[{"id":1,"state_id":5,"district_id":1,"location":"Raipur Railway Station","decibels":78.4,"zone":"commercial","time_of_day":"day","limit_value":65,"status":"exceeded","source":"manual","recorded_at":"2026-03-14T13:11:34.509Z"},{"id":2,"state_id":5,"district_id":4,"location":"Korba Industrial Area","decibels":88.2,"zone":"industrial","time_of_day":"day","limit_value":75,"status":"exceeded","source":"sensor","recorded_at":"2026-03-14T13:11:34.509Z"},{"id":3,"state_id":5,"district_id":1,"location":"Raipur Telibandha Lake","decibels":52.4,"zone":"residential","time_of_day":"day","limit_value":55,"status":"within_limit","source":"manual","recorded_at":"2026-03-14T13:11:34.509Z"},{"id":4,"state_id":14,"district_id":1,"location":"Mumbai Western Express Hwy","decibels":84.2,"zone":"commercial","time_of_day":"day","limit_value":65,"status":"exceeded","source":"sensor","recorded_at":"2026-03-14T13:11:34.509Z"},{"id":5,"state_id":26,"district_id":1,"location":"Lucknow Hazratganj","decibels":74.8,"zone":"commercial","time_of_day":"day","limit_value":65,"status":"exceeded","source":"manual","recorded_at":"2026-03-14T13:11:34.509Z"},{"id":6,"state_id":33,"district_id":1,"location":"Delhi Chandni Chowk","decibels":89.4,"zone":"commercial","time_of_day":"day","limit_value":65,"status":"exceeded","source":"sensor","recorded_at":"2026-03-14T13:11:34.509Z"},{"id":7,"state_id":33,"district_id":4,"location":"South Delhi Hauz Khas","decibels":62.4,"zone":"residential","time_of_day":"day","limit_value":55,"status":"exceeded","source":"manual","recorded_at":"2026-03-14T13:11:34.509Z"},{"id":8,"state_id":11,"district_id":1,"location":"Bengaluru MG Road","decibels":72.8,"zone":"commercial","time_of_day":"day","limit_value":65,"status":"exceeded","source":"sensor","recorded_at":"2026-03-14T13:11:34.509Z"},{"id":9,"state_id":23,"district_id":1,"location":"Chennai Anna Salai","decibels":68.4,"zone":"commercial","time_of_day":"day","limit_value":65,"status":"exceeded","source":"manual","recorded_at":"2026-03-14T13:11:34.509Z"},{"id":10,"state_id":28,"district_id":1,"location":"Kolkata Park Street","decibels":74.2,"zone":"commercial","time_of_day":"day","limit_value":65,"status":"exceeded","source":"sensor","recorded_at":"2026-03-14T13:11:34.509Z"},{"id":11,"state_id":5,"district_id":2,"location":"Bilaspur Vyapam Chowk","decibels":48.8,"zone":"residential","time_of_day":"night","limit_value":45,"status":"exceeded","source":"manual","recorded_at":"2026-03-14T13:11:34.509Z"},{"id":12,"state_id":7,"district_id":1,"location":"Ahmedabad CG Road","decibels":71.2,"zone":"commercial","time_of_day":"day","limit_value":65,"status":"exceeded","source":"sensor","recorded_at":"2026-03-14T13:11:34.509Z"}]